faim_huygens/__init__.py
faim_huygens/parameters.py
faim_huygens/templates.py
faim_huygens-0.3.0.dist-info/METADATA
faim_huygens-0.3.0.dist-info/WHEEL
faim_huygens-0.3.0.dist-info/RECORD
