Metadata-Version: 2.1
Name: faim-huygens
Version: 0.3.0
Summary: Tools to interact with SVI Huygens from Python
Project-URL: Documentation, https://github.com/fmi-faim/faim-huygens#readme
Project-URL: Issues, https://github.com/fmi-faim/faim-huygens/issues
Project-URL: Source, https://github.com/fmi-faim/faim-huygens
Author-email: Jan Eglinger <jan.eglinger@fmi.ch>
License-Expression: MIT
Classifier: Development Status :: 4 - Beta
Classifier: Programming Language :: Python
Classifier: Programming Language :: Python :: 3.7
Classifier: Programming Language :: Python :: 3.8
Classifier: Programming Language :: Python :: 3.9
Classifier: Programming Language :: Python :: 3.10
Classifier: Programming Language :: Python :: 3.11
Classifier: Programming Language :: Python :: Implementation :: CPython
Classifier: Programming Language :: Python :: Implementation :: PyPy
Requires-Python: >=3.7
Requires-Dist: pydantic
Requires-Dist: pyparsing
